kaldiprep/__init__.py
kaldiprep/dictionary.py
kaldiprep/utterances.py
kaldiprep-0.5.1.dist-info/METADATA
kaldiprep-0.5.1.dist-info/WHEEL
kaldiprep-0.5.1.dist-info/top_level.txt
kaldiprep-0.5.1.dist-info/RECORD
