Metadata-Version: 2.1
Name: kaldiprep
Version: 0.5.1
Summary: UNKNOWN
Home-page: https://repo.cslu.ohsu.edu/galer/kaldiprep
Author: Robert Gale
Author-email: galer@ohsu.edu
License: UNKNOWN
Platform: UNKNOWN
Requires-Dist: sortedcontainers
